airo_camera_toolkit/__init__.py
airo_camera_toolkit/cli.py
airo_camera_toolkit/interfaces.py
airo_camera_toolkit/py.typed
airo_camera_toolkit/calibration/__init__.py
airo_camera_toolkit/calibration/collect_calibration_data.py
airo_camera_toolkit/calibration/compute_calibration.py
airo_camera_toolkit/calibration/fiducial_markers.py
airo_camera_toolkit/calibration/hand_eye_calibration.py
airo_camera_toolkit/cameras/__init__.py
airo_camera_toolkit/cameras/camera_discovery.py
airo_camera_toolkit/cameras/manual_test_hw.py
airo_camera_toolkit/cameras/multiprocess/__init__.py
airo_camera_toolkit/cameras/multiprocess/multiprocess_rerun_logger.py
airo_camera_toolkit/cameras/multiprocess/multiprocess_rgb_camera.py
airo_camera_toolkit/cameras/multiprocess/multiprocess_rgbd_camera.py
airo_camera_toolkit/cameras/multiprocess/multiprocess_stereo_rgbd_camera.py
airo_camera_toolkit/cameras/multiprocess/multiprocess_video_recorder.py
airo_camera_toolkit/cameras/multiprocess/multiprocess_zed_camera.py
airo_camera_toolkit/cameras/opencv_videocapture/__init__.py
airo_camera_toolkit/cameras/opencv_videocapture/opencv_videocapture.py
airo_camera_toolkit/cameras/realsense/__init__.py
airo_camera_toolkit/cameras/realsense/realsense.py
airo_camera_toolkit/cameras/realsense/realsense_scan_profiles.py
airo_camera_toolkit/cameras/zed/__init__.py
airo_camera_toolkit/cameras/zed/zed.py
airo_camera_toolkit/cameras/zed/zed2i.py
airo_camera_toolkit/image_transforms/__init__.py
airo_camera_toolkit/image_transforms/composed_transform.py
airo_camera_toolkit/image_transforms/image_transform.py
airo_camera_toolkit/image_transforms/transforms/__init__.py
airo_camera_toolkit/image_transforms/transforms/crop.py
airo_camera_toolkit/image_transforms/transforms/resize.py
airo_camera_toolkit/image_transforms/transforms/rotate90.py
airo_camera_toolkit/pinhole_operations/__init__.py
airo_camera_toolkit/pinhole_operations/projection.py
airo_camera_toolkit/pinhole_operations/triangulation.py
airo_camera_toolkit-2026.1.0.dist-info/METADATA
airo_camera_toolkit-2026.1.0.dist-info/WHEEL
airo_camera_toolkit-2026.1.0.dist-info/entry_points.txt
airo_camera_toolkit-2026.1.0.dist-info/top_level.txt
airo_camera_toolkit-2026.1.0.dist-info/RECORD
